nrt_time_utils/__init__.py
nrt_time_utils/time_utils.py
nrt_time_utils/timer.py
nrt_time_utils/timezone.py
nrt_time_utils-1.0.6.data/data/requirements.txt
nrt_time_utils-1.0.6.dist-info/licenses/LICENSE
nrt_time_utils-1.0.6.dist-info/METADATA
nrt_time_utils-1.0.6.dist-info/WHEEL
nrt_time_utils-1.0.6.dist-info/top_level.txt
nrt_time_utils-1.0.6.dist-info/RECORD
