Metadata-Version: 2.4
Name: nrt-time-utils
Version: 1.0.6
Summary: Time utilities in Python
Home-page: https://github.com/etuzon/python-nrt-time-utils
Author: Eyal Tuzon
Author-email: Eyal Tuzon <eyal.tuzon.dev@gmail.com>
Project-URL: Homepage, https://github.com/etuzon/python-nrt-time-utils
Project-URL: Bug Tracker, https://github.com/etuzon/python-nrt-time-utils/issues
Project-URL: documentation, https://github.com/etuzon/python-nrt-time-utils/wiki
Keywords: python,python3,python-3,tool,tools,time,utilities,utils,util,nrt,nrt-utils,time-utils,time-utilities,nrt-time-utils,nrt-time-utilities
Classifier: Programming Language :: Python :: 3
Classifier: Programming Language :: Python :: 3.8
Classifier: Programming Language :: Python :: 3.9
Classifier: Programming Language :: Python :: 3.10
Classifier: Programming Language :: Python :: 3.11
Classifier: Programming Language :: Python :: 3.12
Classifier: Programming Language :: Python :: 3.13
Classifier: Programming Language :: Python :: 3.14
Classifier: Operating System :: OS Independent
Requires-Python: >=3.8
License-File: LICENSE
Requires-Dist: pytz>=2024.1
Dynamic: author
Dynamic: home-page
Dynamic: license-file
Dynamic: requires-dist
